dagster_databricks/__init__.py
dagster_databricks/configs.py
dagster_databricks/databricks.py
dagster_databricks/databricks_pyspark_step_launcher.py
dagster_databricks/databricks_step_main.py
dagster_databricks/py.typed
dagster_databricks/resources.py
dagster_databricks/solids.py
dagster_databricks/types.py
dagster_databricks/version.py
dagster_databricks-1.0.5.dist-info/LICENSE
dagster_databricks-1.0.5.dist-info/METADATA
dagster_databricks-1.0.5.dist-info/WHEEL
dagster_databricks-1.0.5.dist-info/top_level.txt
dagster_databricks-1.0.5.dist-info/RECORD
